xmatrix/__init__.py
xmatrix/identity_matrix.py
xmatrix/matrix.py
xmatrix-1.4.6.dist-info/LICENSE
xmatrix-1.4.6.dist-info/METADATA
xmatrix-1.4.6.dist-info/WHEEL
xmatrix-1.4.6.dist-info/top_level.txt
xmatrix-1.4.6.dist-info/RECORD
