Metadata-Version: 2.1
Name: xmatrix
Version: 1.4.6
Summary: Help you calculate matrix.
Home-page: https://github.com/Xanonymous-GitHub/xmatrix
Author: Xanonymous
Author-email: trusaidlin@gmail.com
License: UNKNOWN
Platform: all
Classifier: Programming Language :: Python :: 3
Classifier: License :: OSI Approved :: MIT License
Classifier: Operating System :: OS Independent
Requires-Python: >=3.6
